sklearn_extensions
examples
