Metadata-Version: 1.1
Name: sklearn-extensions
Version: 0.0.2
Summary: A bundle of 3rd party extensions to scikit-learn
Home-page: https://github.com/wdm0006/sklearn-extensions
Author: Will McGinnis
Author-email: will@pedalwrencher.com
License: BSD
Keywords: scikit-learn sklearn extensions machine learning
Platform: UNKNOWN
Classifier: Development Status :: 3 - Alpha
Classifier: Intended Audience :: Developers
Classifier: Programming Language :: Python :: 3
